newArithmeticpkg1239/__init__.py
newArithmeticpkg1239/arithmetic.py
newArithmeticpkg1239/test_arithmetic.py
newArithmeticpkg1239-0.1.1.dist-info/LICENSE
newArithmeticpkg1239-0.1.1.dist-info/METADATA
newArithmeticpkg1239-0.1.1.dist-info/WHEEL
newArithmeticpkg1239-0.1.1.dist-info/top_level.txt
newArithmeticpkg1239-0.1.1.dist-info/RECORD
